sergiofrfo_google_de_toolkit/.envrc
sergiofrfo_google_de_toolkit/__init__.py
sergiofrfo_google_de_toolkit/main.py
sergiofrfo_google_de_toolkit/vm.py
sergiofrfo_google_de_toolkit-0.2.0.dist-info/METADATA
sergiofrfo_google_de_toolkit-0.2.0.dist-info/WHEEL
sergiofrfo_google_de_toolkit-0.2.0.dist-info/entry_points.txt
sergiofrfo_google_de_toolkit-0.2.0.dist-info/RECORD
